py_win_task_scheduler/__init__.py
py_win_task_scheduler-0.2.1.dist-info/LICENSE
py_win_task_scheduler-0.2.1.dist-info/METADATA
py_win_task_scheduler-0.2.1.dist-info/WHEEL
py_win_task_scheduler-0.2.1.dist-info/top_level.txt
py_win_task_scheduler-0.2.1.dist-info/RECORD
