Metadata-Version: 2.1
Name: py-win-task-scheduler
Version: 0.2.1
Summary: Script to work with Windows Task Scheduler 2.0 from SaltStack
Home-page: https://github.com/dolamroth/py_win_task_scheduler
Download-URL: https://github.com/dolamroth/py_win_task_scheduler/archive/refs/tags/0.2.1.tar.gz
Author: Sergey Sayamov
Author-email: dolamroth71@gmail.com
License: MIT License
Classifier: Environment :: Win32 (MS Windows)
Classifier: Programming Language :: Python :: 3
Classifier: Programming Language :: Python :: 3 :: Only
Classifier: Programming Language :: Python :: 3.9
Classifier: Programming Language :: Python :: 3.10
Classifier: Programming Language :: Python :: 3.11
Classifier: Programming Language :: Python :: 3.12
Requires-Python: >=3.9
License-File: LICENSE
Requires-Dist: pywin32 (>=306)
